AttrDict_Slim/Dict.py
AttrDict_Slim/__init__.py
AttrDict_Slim-0.0.1.dist-info/LICENSE
AttrDict_Slim-0.0.1.dist-info/METADATA
AttrDict_Slim-0.0.1.dist-info/WHEEL
AttrDict_Slim-0.0.1.dist-info/top_level.txt
AttrDict_Slim-0.0.1.dist-info/RECORD
